odoo10_addon_l10n_es_aeat_sii_cash_basis-10.0.1.0.0.99.dev7-py3.8-nspkg.pth
odoo/addons/l10n_es_aeat_sii_cash_basis/README.rst
odoo/addons/l10n_es_aeat_sii_cash_basis/__init__.py
odoo/addons/l10n_es_aeat_sii_cash_basis/__manifest__.py
odoo/addons/l10n_es_aeat_sii_cash_basis/data/aeat_sii_payment_mode_key_data.xml
odoo/addons/l10n_es_aeat_sii_cash_basis/i18n/es.po
odoo/addons/l10n_es_aeat_sii_cash_basis/i18n/l10n_es_aeat_sii_cash_basis.pot
odoo/addons/l10n_es_aeat_sii_cash_basis/models/__init__.py
odoo/addons/l10n_es_aeat_sii_cash_basis/models/account_invoice.py
odoo/addons/l10n_es_aeat_sii_cash_basis/models/account_partial_reconcile.py
odoo/addons/l10n_es_aeat_sii_cash_basis/models/account_payment_method.py
odoo/addons/l10n_es_aeat_sii_cash_basis/models/account_payment_mode.py
odoo/addons/l10n_es_aeat_sii_cash_basis/models/aeat_sii_payment_mode_key.py
odoo/addons/l10n_es_aeat_sii_cash_basis/readme/CONFIGURE.rst
odoo/addons/l10n_es_aeat_sii_cash_basis/readme/CONTRIBUTORS.rst
odoo/addons/l10n_es_aeat_sii_cash_basis/readme/DESCRIPTION.rst
odoo/addons/l10n_es_aeat_sii_cash_basis/readme/USAGE.rst
odoo/addons/l10n_es_aeat_sii_cash_basis/security/ir.model.access.csv
odoo/addons/l10n_es_aeat_sii_cash_basis/static/description/icon.png
odoo/addons/l10n_es_aeat_sii_cash_basis/static/description/index.html
odoo/addons/l10n_es_aeat_sii_cash_basis/tests/__init__.py
odoo/addons/l10n_es_aeat_sii_cash_basis/tests/test_cash_basis_sii.py
odoo/addons/l10n_es_aeat_sii_cash_basis/views/account_invoice_views.xml
odoo/addons/l10n_es_aeat_sii_cash_basis/views/account_payment_method_views.xml
odoo/addons/l10n_es_aeat_sii_cash_basis/views/account_payment_mode_views.xml
odoo/addons/l10n_es_aeat_sii_cash_basis/views/aeat_sii_payment_mode_key_view.xml
odoo10_addon_l10n_es_aeat_sii_cash_basis-10.0.1.0.0.99.dev7.dist-info/METADATA
odoo10_addon_l10n_es_aeat_sii_cash_basis-10.0.1.0.0.99.dev7.dist-info/WHEEL
odoo10_addon_l10n_es_aeat_sii_cash_basis-10.0.1.0.0.99.dev7.dist-info/namespace_packages.txt
odoo10_addon_l10n_es_aeat_sii_cash_basis-10.0.1.0.0.99.dev7.dist-info/top_level.txt
odoo10_addon_l10n_es_aeat_sii_cash_basis-10.0.1.0.0.99.dev7.dist-info/RECORD
